flair/__init__.py
flair/__main__.py
flair/platforms.py
flair/augment/__init__.py
flair/augment/cli.py
flair/augment/clipboard.py
flair/augment/screenshot.py
flair/hook/__init__.py
flair/hook/input.py
flair/hook/process/__init__.py
flair/hook/process/linux.py
flair/hook/process/win32.py
flair/hook/storage/__init__.py
flair/hook/storage/linux.py
flair/hook/storage/win32.py
flair/hook/window/__init__.py
flair/hook/window/linux.py
flair/hook/window/win32.py
flair/inspect/__init__.py
flair/inspect/events.py
flair/inspect/state.py
fl_flair-0.5.2.dist-info/LICENSE.md
fl_flair-0.5.2.dist-info/METADATA
fl_flair-0.5.2.dist-info/WHEEL
fl_flair-0.5.2.dist-info/top_level.txt
fl_flair-0.5.2.dist-info/RECORD
