Metadata-Version: 2.1
Name: fl-flair
Version: 0.5.2
Summary: A novel client-side hook for Freelancer
Home-page: https://github.com/biqqles/flair
Author: biqqles
Author-email: biqqles@protonmail.com
License: UNKNOWN
Platform: UNKNOWN
Classifier: Programming Language :: Python :: 3
Classifier: License :: OSI Approved :: Mozilla Public License 2.0 (MPL 2.0)
Classifier: Operating System :: Microsoft :: Windows
Classifier: Operating System :: POSIX :: Linux
Classifier: Topic :: Games/Entertainment
Classifier: Intended Audience :: Developers
Classifier: Development Status :: 3 - Alpha
Requires-Python: >=3.6
Requires-Dist: deconstruct
Requires-Dist: fl-flint (>=0.8.1)
Requires-Dist: keyboard (>=0.11.0)
Requires-Dist: Pillow
Requires-Dist: pyperclip
Requires-Dist: python-xlib ; platform_system == "Linux"
Requires-Dist: rpyc ; platform_system == "Linux"
Requires-Dist: virtualkeys ; platform_system == "Linux"
Requires-Dist: pywin32 ; platform_system == "Windows"
